{"name":"Calmdown-vipbox","tagline":"no more ad and popup","body":"### Welcome calmdown-vipbox Page!\r\n======================\r\n\r\n[![wercker status](https://app.wercker.com/status/20ef247a06d88af36865a5c5c85a4065/m \"wercker status\")](https://app.wercker.com/project/bykey/20ef247a06d88af36865a5c5c85a4065)\r\n\r\n## Download\r\n[Chrome Webstore](https://chrome.google.com/webstore/detail/calm-down-vipbox/mmdakmbanhoikfpamdjjgcnepcholaei)\r\n\r\n### Authors and Contributors\r\nIn 2014, Takashi Fujita(@tgfjt).\r\n\r\n### Support or Contact\r\n[Create a new Issue](https://github.com/tgfjt/calmdown-vipbox/issues/new)","google":"","note":"Don't delete this file! It's used internally to help with page regeneration."}